deepmcp/__init__.py
deepmcp/client.py
deepmcp/main.py
deepmcp/server.py
deepmcp-0.2.8.dist-info/WHEEL
deepmcp-0.2.8.dist-info/entry_points.txt
deepmcp-0.2.8.dist-info/METADATA
deepmcp-0.2.8.dist-info/RECORD
