Metadata-Version: 2.3
Name: deepmcp
Version: 0.2.8
Summary: a calculator mcp server
Requires-Dist: fastmcp>=2.8.0
Requires-Dist: mcp==1.9.2
Requires-Dist: nacos-mcp-wrapper-python>=1.0.9
Requires-Dist: openai>=1.108.0
Requires-Python: >=3.12
